nosible/__init__.py
nosible/nosible_client.py
nosible/classes/result.py
nosible/classes/result_set.py
nosible/classes/search.py
nosible/classes/search_set.py
nosible/classes/snippet.py
nosible/classes/snippet_set.py
nosible/classes/web_page.py
nosible/utils/json_tools.py
nosible/utils/rate_limiter.py
nosible-0.3.6.dist-info/licenses/LICENSE
nosible-0.3.6.dist-info/METADATA
nosible-0.3.6.dist-info/WHEEL
nosible-0.3.6.dist-info/top_level.txt
nosible-0.3.6.dist-info/RECORD
