Metadata-Version: 2.4
Name: nosible
Version: 0.3.6
Summary: Python client for the NOSIBLE Search API
Home-page: https://github.com/NosibleAI/nosible-py
Author: Stuart Reid, Matthew Dicks, Richard Taylor, Gareth Warburton
Author-email: Stuart Reid <stuart@nosible.com>, Matthew Dicks <matthew@nosible.com>, Richard Taylor <richard@nosible.com>, Gareth Warburton <gareth@nosible.com>
License-Expression: MIT
Project-URL: Homepage, https://github.com/NosibleAI/nosible-py
Project-URL: Documentation, https://nosible-py.readthedocs.io/en/latest/
Classifier: Development Status :: 4 - Beta
Classifier: Intended Audience :: Developers
Classifier: Programming Language :: Python :: 3
Classifier: Programming Language :: Python :: 3 :: Only
Classifier: Topic :: Software Development :: Libraries
Classifier: Topic :: Internet :: WWW/HTTP :: Indexing/Search
Classifier: Intended Audience :: Information Technology
Classifier: Intended Audience :: Science/Research
Classifier: Intended Audience :: Financial and Insurance Industry
Classifier: Programming Language :: Python :: 3.9
Classifier: Programming Language :: Python :: 3.10
Classifier: Programming Language :: Python :: 3.11
Classifier: Programming Language :: Python :: 3.12
Classifier: Programming Language :: Python :: 3.13
Classifier: Topic :: Software Development :: Libraries :: Python Modules
Classifier: Operating System :: OS Independent
Requires-Python: >=3.9
License-File: LICENSE
Requires-Dist: polars
Requires-Dist: duckdb
Requires-Dist: openai
Requires-Dist: tantivy
Requires-Dist: pyrate-limiter
Requires-Dist: tenacity
Requires-Dist: cryptography
Requires-Dist: pyarrow
Requires-Dist: pandas
Dynamic: author
Dynamic: home-page
Dynamic: license-file
Dynamic: requires-python
